data_path_utils/__init__.py
data_path_utils/archive_script_data_dependencies.py
data_path_utils/delete_empty_data_paths.py
data_path_utils/dependency_graph.py
data_path_utils/list_script_dependencies.py
data_path_utils-0.8.1.dist-info/METADATA
data_path_utils-0.8.1.dist-info/RECORD
data_path_utils-0.8.1.dist-info/WHEEL
data_path_utils-0.8.1.dist-info/entry_points.txt
data_path_utils-0.8.1.dist-info/top_level.txt
