Metadata-Version: 2.1
Name: data-path-utils
Version: 0.8.1
Summary: Management of scripts that produce/consume data with specific labels
Home-page: https://github.com/mruffalo/data-path-utils
Author: Matt Ruffalo
Author-email: matt.ruffalo@gmail.com
License: MIT
Keywords: data-dependencies development
Platform: UNKNOWN
Classifier: Development Status :: 4 - Beta
Classifier: Intended Audience :: Developers
Classifier: Intended Audience :: Science/Research
Classifier: Topic :: Software Development
Classifier: License :: OSI Approved :: MIT License
Classifier: Programming Language :: Python :: 3 :: Only
Classifier: Programming Language :: Python :: 3.6
Requires-Python: >=3.6
Provides-Extra: plotting
Provides-Extra: plotting
Requires-Dist: networkx; extra == 'plotting'
Requires-Dist: pydotplus; extra == 'plotting'
